src/__init__.py
src/main.py
haiku_ollama-0.1.0.dist-info/LICENSE
haiku_ollama-0.1.0.dist-info/METADATA
haiku_ollama-0.1.0.dist-info/WHEEL
haiku_ollama-0.1.0.dist-info/entry_points.txt
haiku_ollama-0.1.0.dist-info/top_level.txt
haiku_ollama-0.1.0.dist-info/RECORD
