Metadata-Version: 2.2
Name: haiku-ollama
Version: 0.1.0
Summary: A command-line interface for interacting with Ollama AI models
Home-page: https://github.com/haikentcode/haiku
Author: Hitesh Regar
Author-email: haikent.work@gmail.com
License: MIT
Project-URL: Bug Tracker, https://github.com/haikentcode/haiku/issues
Classifier: Programming Language :: Python :: 3
Classifier: License :: OSI Approved :: MIT License
Classifier: Operating System :: OS Independent
Classifier: Environment :: Console
Classifier: Topic :: Utilities
Requires-Python: >=3.8
License-File: LICENSE
Requires-Dist: ollama
Requires-Dist: rich
Dynamic: author
Dynamic: author-email
Dynamic: classifier
Dynamic: description
Dynamic: description-content-type
Dynamic: home-page
Dynamic: license
Dynamic: project-url
Dynamic: requires-dist
Dynamic: requires-python
Dynamic: summary
